gossip/__init__.py
gossip/_compat.py
gossip/blueprint.py
gossip/exception_policy.py
gossip/exceptions.py
gossip/groups.py
gossip/helpers.py
gossip/hooks.py
gossip/registration.py
gossip/registry.py
gossip/utils.py
gossip/contrib/__init__.py
gossip/contrib/sphinx_ext.py
gossip-2.5.0.dist-info/METADATA
gossip-2.5.0.dist-info/WHEEL
gossip-2.5.0.dist-info/licenses/LICENSE
gossip-2.5.0.dist-info/RECORD
