Metadata-Version: 2.4
Name: gossip
Version: 2.5.0
Summary: Signaling and hooking library
Project-URL: Homepage, https://github.com/getslash/gossip
Author-email: Rotem Yaari <vmalloc@gmail.com>
License: BSD 3-Clause License
License-File: LICENSE
Classifier: Programming Language :: Python :: 3.8
Classifier: Programming Language :: Python :: 3.9
Classifier: Programming Language :: Python :: 3.10
Classifier: Programming Language :: Python :: 3.11
Classifier: Programming Language :: Python :: 3.12
Classifier: Programming Language :: Python :: 3.13
Requires-Python: >=3.8
Requires-Dist: logbook>=0.12.0
Requires-Dist: sentinels
Requires-Dist: vintage
Provides-Extra: doc
Requires-Dist: alabaster; extra == 'doc'
Requires-Dist: docutils; extra == 'doc'
Requires-Dist: releases; extra == 'doc'
Requires-Dist: sphinx>=1.7.1; extra == 'doc'
Provides-Extra: testing
Requires-Dist: munch; extra == 'testing'
Requires-Dist: pylint; extra == 'testing'
Requires-Dist: pytest; extra == 'testing'
